{"flightInformation":[{"depart":"Departing at 12:10 PM","arrive":"Arriving at 12:36 AM JFK Origin New York, NY, US (JFK) 12H, 26M ","stops":"3","duration":"Duration 12 hours and 26 minutes","price":" Economy 2 tickets left at this price,  $900 First (2-cabin) 2 tickets left at this price Mixed cabin $1,282 "},{"depart":"Departing at 12:10 PM","arrive":"Arriving at 12:36 AM JFK Origin New York, NY, US (JFK) 12H, 26M ","stops":"3","duration":"Duration 12 hours and 26 minutes","price":" Economy 2 tickets left at this price,  $1,020 First (2-cabin) 2 tickets left at this price Mixed cabin $1,402"}]}